MANIFEST.in
README.md
setup.py
python_ctags3.egg-info/PKG-INFO
python_ctags3.egg-info/SOURCES.txt
python_ctags3.egg-info/dependency_links.txt
python_ctags3.egg-info/top_level.txt
src/_readtags.c
src/readtags.c
src/ctags/__init__.py
src/examples/example.py
src/examples/tags
src/include/readtags.h
tests/__init__.py
tests/test_ctags.py
tests/test_import.py